{"cameraMode":{"drawMode":0,"name":"Shaded","section":"Shading Mode"},"sceneLighting":false,"audioPlay":false,"sceneViewState":{"m_AlwaysRefresh":false,"showFog":true,"showSkybox":false,"showFlares":true,"showImageEffects":true,"showParticleSystems":true,"showVisualEffectGraphs":true,"m_FxEnabled":true},"in2DMode":false,"pivot":{"x":-9.215353965759278,"y":-7.868195533752441,"z":84.91073608398438},"rotation":{"x":0.054807111620903018,"y":-0.04489483684301376,"z":0.002690082648769021,"w":0.9975824356079102},"size":49.86020278930664,"orthographic":false}